LICENSE
MANIFEST.in
README.rst
setup.py
django_gatehouse.egg-info/PKG-INFO
django_gatehouse.egg-info/SOURCES.txt
django_gatehouse.egg-info/dependency_links.txt
django_gatehouse.egg-info/top_level.txt
gatehouseapp/__init__.py
gatehouseapp/admin.py
gatehouseapp/filters.py
gatehouseapp/forms.py
gatehouseapp/models.py
gatehouseapp/tests.py
gatehouseapp/urls.py
gatehouseapp/views.py
gatehouseapp/migrations/0001_initial.py
gatehouseapp/migrations/__init__.py
gatehouseapp/templates/__init__.py
gatehouseapp/templates/base.html
gatehouseapp/templates/gatehouseapp/__init__.py
gatehouseapp/templates/gatehouseapp/addvisit.html
gatehouseapp/templates/gatehouseapp/arch.html
gatehouseapp/templates/gatehouseapp/catering.html
gatehouseapp/templates/gatehouseapp/delete.html
gatehouseapp/templates/gatehouseapp/index.html
gatehouseapp/templates/gatehouseapp/todaygatehousepersonlist.html
gatehouseapp/templates/gatehouseapp/update.html
gatehouseapp/templates/gatehouseapp/visitdata_list.html
gatehouseapp/templates/registration/__init__.py
gatehouseapp/templates/registration/login.html